aanalyticsact/__init__.py
aanalyticsact/__version__.py
aanalyticsact/actExecute.py
aanalyticsact/actModuler.py
aanalyticsact/actRunner.py
aanalyticsact-0.0.1.47.dist-info/METADATA
aanalyticsact-0.0.1.47.dist-info/WHEEL
aanalyticsact-0.0.1.47.dist-info/top_level.txt
aanalyticsact-0.0.1.47.dist-info/RECORD
