Metadata-Version: 2.1
Name: aanalyticsact
Version: 0.0.1.47
Summary: adobe analytics library for Team ACT
Home-page: https://github.com/SunkyeongLee/aanalyticsact
Author: Sunkyeong Lee
Author-email: sunkyeong.lee@concentrix.com
Classifier: Programming Language :: Python :: 3
Classifier: License :: OSI Approved :: MIT License
Classifier: Operating System :: OS Independent
Requires-Python: >=3.6
